{
  "project_info": {
    "project_number": "127901953489",
    "project_id": "uac2-7d0f9",
    "storage_bucket": "uac2-7d0f9.appspot.com"
  },
  "client": [
    {
      "client_info": {
        "mobilesdk_app_id": "1:127901953489:android:02cb55ff82004bb03fc4f0",
        "android_client_info": {
          "package_name": "com.example.ultimate_alarm_clock"
        }
      },
      "oauth_client": [
        {
          "client_id": "127901953489-lnsmj324f5eutudkjvaidotj99bq1l47.apps.googleusercontent.com",
          "client_type": 3
        }
      ],
      "api_key": [
        {
          "current_key": "AIzaSyCEaWUdYF_PnGFu0uJL8Zl_BlT8knDVeHg"
        }
      ],
      "services": {
        "appinvite_service": {
          "other_platform_oauth_client": [
            {
              "client_id": "127901953489-lnsmj324f5eutudkjvaidotj99bq1l47.apps.googleusercontent.com",
              "client_type": 3
            }
          ]
        }
      }
    }
  ],
  "configuration_version": "1"
}